csvgroup/__init__.py
csvgroup/__main__.py
csvgroup/utils.py
csvgroup_cupack-0.1.0.dist-info/METADATA
csvgroup_cupack-0.1.0.dist-info/WHEEL
csvgroup_cupack-0.1.0.dist-info/top_level.txt
csvgroup_cupack-0.1.0.dist-info/RECORD
